pybots/VERSION.txt
pybots/__info__.py
pybots/__init__.py
pybots/apis/__init__.py
pybots/apis/security/__init__.py
pybots/apis/security/virustotal.py
pybots/apis/security/data_breaches/__init__.py
pybots/apis/security/data_breaches/dehashed.py
pybots/apis/security/data_breaches/ghostproject.py
pybots/apis/security/data_breaches/haveibeenpwned.py
pybots/apis/security/data_breaches/haveibeensold.py
pybots/apis/security/data_breaches/nuclearleaks.py
pybots/apis/security/default_credentials/__init__.py
pybots/apis/security/default_credentials/cirtnet.py
pybots/apis/security/default_credentials/datarecovery.py
pybots/apis/security/default_credentials/passworddb.py
pybots/apis/security/default_credentials/routerpasswd.py
pybots/apis/security/default_credentials/saynamweb.py
pybots/apis/security/exposed_devices/__init__.py
pybots/apis/security/exposed_devices/censys.py
pybots/apis/security/exposed_devices/shodan.py
pybots/bots/__init__.py
pybots/bots/ctf/__init__.py
pybots/bots/ctf/ringzero.py
pybots/bots/ctf/rootme.py
pybots/bots/ctf/zsis.py
pybots/bots/security/__init__.py
pybots/bots/security/censys.py
pybots/bots/security/ghostproject.py
pybots/bots/security/haveibeenpwned.py
pybots/bots/security/haveibeensold.py
pybots/bots/security/nuclearleaks.py
pybots/bots/security/shodan.py
pybots/bots/utils/__init__.py
pybots/bots/utils/git.py
pybots/bots/utils/postbin.py
pybots/core/__init__.py
pybots/core/ssocket.py
pybots/core/template.py
pybots/core/web.py
pybots/core/mixins/__init__.py
pybots/core/mixins/crawler.py
pybots/core/mixins/downloader.py
pybots/core/mixins/mailer.py
pybots/core/mixins/proxy.py
pybots/core/protocols/__init__.py
pybots/core/protocols/http.py
pybots/core/protocols/irc.py
pybots/core/protocols/tcp.py
pybots/core/utils/__init__.py
pybots/core/utils/api.py
pybots/core/utils/cloudflare.py
pybots/core/utils/common.py
pybots/core/utils/ip.py
pybots/core/utils/proxy.py
pybots-2.1.5.dist-info/LICENSE
pybots-2.1.5.dist-info/METADATA
pybots-2.1.5.dist-info/WHEEL
pybots-2.1.5.dist-info/top_level.txt
pybots-2.1.5.dist-info/RECORD
