Metadata-Version: 2.1
Name: pybots
Version: 2.1.5
Summary: Devkit for quickly creating client robots for remote communications
Author-email: Alexandre D'Hondt <alexandre.dhondt@gmail.com>
License: GNU GENERAL PUBLIC LICENSE
Project-URL: documentation, https://python-pybots.readthedocs.io/en/latest/?badge=latest
Project-URL: homepage, https://github.com/dhondta/python-pybots
Project-URL: issues, https://github.com/dhondta/python-pybots/issues
Project-URL: repository, https://github.com/dhondta/python-pybots
Keywords: python,development,programming,framework,cli,devkit,robots
Classifier: Development Status :: 5 - Production/Stable
Classifier: Environment :: Console
Classifier: Intended Audience :: Developers
Classifier: License :: OSI Approved :: GNU General Public License v3 or later (GPLv3+)
Classifier: Programming Language :: Python :: 3
Classifier: Programming Language :: Python :: 3.8
Classifier: Programming Language :: Python :: 3.9
Classifier: Programming Language :: Python :: 3.10
Classifier: Programming Language :: Python :: 3.11
Classifier: Programming Language :: Python :: 3.12
Classifier: Topic :: Software Development :: Libraries :: Python Modules
Requires-Python: <4,>=3.7
License-File: LICENSE
Requires-Dist: beautifulsoup4 >=4.12.3
Requires-Dist: pycountry >=24.6.1
Requires-Dist: requests >=2.32.2
Requires-Dist: simplejson >=3.19.3
Requires-Dist: tinyscript >=1.30.16
Requires-Dist: urllib3 >=1.26.19
Requires-Dist: user-agent >=0.1.10
